    <reports org='nttcom' name='skyway-siru-client'>
  <reporting class='repo-report' repo='nttcom/skyway-siru-client' type='WikiOnDbReporter'><field>2017-06-02 21:03:53 +0000</field><field>nttcom/skyway-siru-client</field><field>https://github.com/nttcom/skyway-siru-client/wiki</field></reporting>
  <reporting class='issue-report' type='LabelCountDbReporter'><field>nttcom/skyway-siru-client</field><field>2</field><field>0</field><field>2</field><field>0</field><field>0</field><field>0</field><field>0</field></reporting>
  <reporting class='issue-report' type='LabelDbReporter'><field><label color='0e8a16'>just a task</label></field><field>1</field></reporting>  <reporting class='issue-report' type='LabelDbReporter'><field><label color='ee0701'>bug</label></field><field>2</field></reporting>  <reporting class='issue-report' type='LabelDbReporter'><field><label color='84b6eb'>enhancement</label></field><field>2</field></reporting>  <reporting class='issue-report' repo='nttcom/skyway-siru-client' type='AverageIssueCloseDbReporter'><field>nttcom/skyway-siru-client</field><field>0</field><field>0</field><field>0</field><field>0</field><field>0</field><field>0</field><field>0</field><field>0</field><field>0</field><field>5</field><field>1.0</field><field>0</field></reporting>
  <reporting class='issue-report' repo='nttcom/skyway-siru-client' type='AveragePrCloseDbReporter'><field>nttcom/skyway-siru-client</field><field>0</field><field>0</field><field>0</field><field>0</field><field>0</field><field>0</field><field>0</field><field>0</field><field>0</field><field>2</field><field>0.0</field><field>0</field></reporting>
    </reports>
