    <reports org='nttcom' name='terraform-provider-ecl'>
  <reporting class='repo-report' repo='nttcom/terraform-provider-ecl' type='WikiOnDbReporter'><field>2019-03-25 00:59:45 +0000</field><field>nttcom/terraform-provider-ecl</field><field>https://github.com/nttcom/terraform-provider-ecl/wiki</field></reporting>
  <reporting class='issue-report' type='LabelCountDbReporter'><field>nttcom/terraform-provider-ecl</field><field>0</field><field>0</field><field>0</field><field>0</field><field>0</field><field>0</field><field>0</field></reporting>
  <reporting class='issue-report' repo='nttcom/terraform-provider-ecl' type='AverageIssueCloseDbReporter'><field>nttcom/terraform-provider-ecl</field><field>0</field><field>0</field><field>0</field><field>0</field><field>0</field><field>0</field><field>2</field><field>122.0</field><field>0</field><field>4</field><field>63.5</field><field>0</field></reporting>
  <reporting class='issue-report' repo='nttcom/terraform-provider-ecl' type='AveragePrCloseDbReporter'><field>nttcom/terraform-provider-ecl</field><field>0</field><field>0</field><field>0</field><field>5</field><field>22.8</field><field>0</field><field>48</field><field>5.46</field><field>0</field><field>68</field><field>9.74</field><field>0</field></reporting>
    </reports>
